Metadata-Version: 2.1
Name: einx
Version: 0.3.0
Summary: Universal Tensor Operations in Einstein-Inspired Notation for Python
Home-page: https://github.com/fferflo/einx
Author: Florian Fervers
Author-email: florian.fervers@gmail.com
License: MIT
Classifier: Development Status :: 3 - Alpha
Classifier: Intended Audience :: Developers
Classifier: License :: OSI Approved :: MIT License
Classifier: Programming Language :: Python :: 3
Requires-Python: >=3.8
License-File: LICENSE
Requires-Dist: numpy
Requires-Dist: sympy
Requires-Dist: frozendict
Provides-Extra: torch
Requires-Dist: torch>=2; extra == "torch"
Provides-Extra: keras
Requires-Dist: keras>=3; extra == "keras"
